structmsig/__init__.py
structmsig/data_model.py
structmsig/nodal_struct.py
structmsig/sequential_struct.py
structmsig/utils.py
structmsig-1.0.0.dist-info/LICENSE
structmsig-1.0.0.dist-info/METADATA
structmsig-1.0.0.dist-info/WHEEL
structmsig-1.0.0.dist-info/top_level.txt
structmsig-1.0.0.dist-info/RECORD
