Metadata-Version: 2.1
Name: structmsig
Version: 1.0.0
Summary: Structured multi-signature (StructMSIG) is a signature protocol that can represent the signing structure of multiple signers who can only sign the specified scope of data.
Home-page: https://github.com/ucanlab/struct-multi-sig
Author: Wei-Tsung Su
Author-email: ellington.su@gmail.com
Classifier: Programming Language :: Python :: 3
Classifier: License :: OSI Approved :: MIT License
Classifier: Operating System :: OS Independent
Requires-Python: >=3.6
License-File: LICENSE
Requires-Dist: ecdsa>=0.19.0
Requires-Dist: pydantic>=2.9.2
Requires-Dist: pyOpenSSL>=24.2.1
